base64_converter/__init__.py
base64_converter/main.py
base64_converter-0.1.0.dist-info/entry_points.txt
base64_converter-0.1.0.dist-info/LICENSE
base64_converter-0.1.0.dist-info/WHEEL
base64_converter-0.1.0.dist-info/METADATA
base64_converter-0.1.0.dist-info/RECORD
